codeset_gym/__init__.py
codeset_gym/__main__.py
codeset_gym/main.py
codeset_gym/test_collectors/__init__.py
codeset_gym/test_collectors/collector.py
codeset_gym/test_collectors/core_collector.py
codeset_gym/test_collectors/core_factory.py
codeset_gym/test_collectors/cpp.py
codeset_gym/test_collectors/csharp.py
codeset_gym/test_collectors/factory.py
codeset_gym/test_collectors/go.py
codeset_gym/test_collectors/java.py
codeset_gym/test_collectors/javascript.py
codeset_gym/test_collectors/python.py
codeset_gym/test_collectors/rust.py
codeset_gym-0.2.1.dist-info/licenses/LICENSE
codeset_gym-0.2.1.dist-info/METADATA
codeset_gym-0.2.1.dist-info/WHEEL
codeset_gym-0.2.1.dist-info/entry_points.txt
codeset_gym-0.2.1.dist-info/top_level.txt
codeset_gym-0.2.1.dist-info/RECORD
